imio.gdpr-1.2.3-py3.12-nspkg.pth
imio/gdpr/__init__.py
imio/gdpr/configure.zcml
imio/gdpr/interfaces.py
imio/gdpr/permissions.zcml
imio/gdpr/setuphandlers.py
imio/gdpr/testing.py
imio/gdpr/testing.zcml
imio/gdpr/upgrades.py
imio/gdpr/upgrades.zcml
imio/gdpr/browser/__init__.py
imio/gdpr/browser/configure.zcml
imio/gdpr/browser/controlpanel.py
imio/gdpr/browser/default_cookies_text.pt
imio/gdpr/browser/default_gdpr_text.pt
imio/gdpr/browser/view.pt
imio/gdpr/browser/views.py
imio/gdpr/browser/overrides/.gitkeep
imio/gdpr/browser/static/.gitkeep
imio/gdpr/browser/static/gdpr.png
imio/gdpr/browser/static/less/styles.less
imio/gdpr/browser/static/less/variables.less
imio/gdpr/locales/imio.gdpr.pot
imio/gdpr/locales/update.sh
imio/gdpr/locales/en/LC_MESSAGES/imio.gdpr.po
imio/gdpr/locales/fr/LC_MESSAGES/imio.gdpr.po
imio/gdpr/locales/nl/LC_MESSAGES/imio.gdpr.po
imio/gdpr/profiles/default/browserlayer.xml
imio/gdpr/profiles/default/catalog.xml
imio/gdpr/profiles/default/controlpanel.xml
imio/gdpr/profiles/default/lessregistry.xml
imio/gdpr/profiles/default/metadata.xml
imio/gdpr/profiles/default/registry.xml
imio/gdpr/profiles/default/rolemap.xml
imio/gdpr/profiles/uninstall/browserlayer.xml
imio/gdpr/profiles/uninstall/registry.xml
imio/gdpr/tests/__init__.py
imio/gdpr/tests/test_cookies_view.py
imio/gdpr/tests/test_gdpr_view.py
imio/gdpr/tests/test_robot.py
imio/gdpr/tests/test_setup.py
imio/gdpr/tests/robot/test_example.robot
imio.gdpr-1.2.3.dist-info/LICENSE.GPL
imio.gdpr-1.2.3.dist-info/LICENSE.rst
imio.gdpr-1.2.3.dist-info/METADATA
imio.gdpr-1.2.3.dist-info/WHEEL
imio.gdpr-1.2.3.dist-info/entry_points.txt
imio.gdpr-1.2.3.dist-info/namespace_packages.txt
imio.gdpr-1.2.3.dist-info/top_level.txt
imio.gdpr-1.2.3.dist-info/RECORD
