Metadata-Version: 2.1
Name: imio.gdpr
Version: 1.2.3
Summary: View and configuration panel to set GDPR information
Home-page: https://pypi.python.org/pypi/imio.gdpr
Author: Benoit Suttor
Author-email: bsuttor@imio.be
License: GPL version 2
Keywords: Python Plone
Classifier: Environment :: Web Environment
Classifier: Framework :: Plone
Classifier: Framework :: Plone :: 5.0
Classifier: Framework :: Plone :: 5.1
Classifier: Programming Language :: Python
Classifier: Programming Language :: Python :: 2.7
Classifier: Operating System :: OS Independent
Classifier: License :: OSI Approved :: GNU General Public License v2 (GPLv2)
License-File: LICENSE.GPL
License-File: LICENSE.rst
Requires-Dist: plone.api >=1.8.4
Requires-Dist: Products.GenericSetup >=1.8.2
Requires-Dist: setuptools
Requires-Dist: z3c.jbot
Requires-Dist: plone.app.dexterity
Requires-Dist: plone.schema
Provides-Extra: test
Requires-Dist: plone.app.testing ; extra == 'test'
Requires-Dist: plone.app.contenttypes ; extra == 'test'
Requires-Dist: plone.testing ; extra == 'test'
Requires-Dist: plone.app.robotframework[debug] ; extra == 'test'
Requires-Dist: ipdb ; extra == 'test'
